leapfrog/__init__.py
leapfrog-0.0.1.dist-info/WHEEL
leapfrog-0.0.1.dist-info/METADATA
leapfrog-0.0.1.dist-info/RECORD
