Metadata-Version: 2.1
Name: leapfrog
Version: 0.0.1
Summary: Boost productivity by using a range of tools helping with ETL, modelling, reporting, and dashboards
Author: Jan Beitner
Requires-Python: >=3.7,<4.0
Classifier: Intended Audience :: Developers
Classifier: Programming Language :: Python :: 3
Classifier: Programming Language :: Python :: 3.7
Classifier: Programming Language :: Python :: 3.8
Provides-Extra: circleci
Requires-Dist: Flask-Session (>=0.3.1)
Requires-Dist: argon2-cffi (>=19.2.0)
Requires-Dist: black
Requires-Dist: dash (>=1.7.0)
Requires-Dist: dash-bootstrap-components (>=0.8.1)
Requires-Dist: dash-extra-components (>=0.0.1)
Requires-Dist: dash-table (>=4.5.1)
Requires-Dist: dill (>=0.3.1.1)
Requires-Dist: dlib (>=19.19.0); sys_platform == "linux"
Requires-Dist: docutils (>=0.16)
Requires-Dist: fastparquet (>=0.3.2)
Requires-Dist: flask_caching (>=1.3.3)
Requires-Dist: flask_login (>=0.4.1)
Requires-Dist: ipykernel (>=5.1.0)
Requires-Dist: libsass (>=0.19.4)
Requires-Dist: matplotlib (>=3.1.2)
Requires-Dist: pandas (>=0.25.3)
Requires-Dist: papermill (>=1.2.1)
Requires-Dist: pexpect (>=4.7.0)
Requires-Dist: plotly (>=4.4.1)
Requires-Dist: psutil (>=5.6.7)
Requires-Dist: pyarrow (>=0.15.1)
Requires-Dist: pytest-circleci-parallelized; extra == "circleci"
Requires-Dist: python-box (>=4.2.3)
Requires-Dist: python-snappy (>=0.5.4); sys_platform == "linux"
Requires-Dist: redis (>=3.3.11)
Requires-Dist: ruamel.yaml (>=0.15.8)
Requires-Dist: scikit-image (>=0.15.0)
Requires-Dist: scikit-learn (>=0.22.1)
Requires-Dist: shap (>=0.34.0)
Requires-Dist: sklearn-pandas (>=1.8.0)
Requires-Dist: statsmodels (>=00.10.2)
Requires-Dist: tables (>=3.6.1)
Requires-Dist: tqdm (>=4.41.1)
Requires-Dist: werkzeug (<1.0)
Requires-Dist: xlsxwriter (>=1.2.7)
